vcs/__init__.py
vcs/_config.py
vcs/scorer.py
vcs/_mapping_windows/__init__.py
vcs/_mapping_windows/_mapping_windows.py
vcs/_matching/__init__.py
vcs/_matching/_best_match.py
vcs/_metrics/__init__.py
vcs/_metrics/_gas/__init__.py
vcs/_metrics/_gas/_gas.py
vcs/_metrics/_las/__init__.py
vcs/_metrics/_las/_las.py
vcs/_metrics/_nas/__init__.py
vcs/_metrics/_nas/_nas.py
vcs/_metrics/_nas/_nas_components/__init__.py
vcs/_metrics/_nas/_nas_components/_distance_nas/__init__.py
vcs/_metrics/_nas/_nas_components/_distance_nas/_distance_nas.py
vcs/_metrics/_nas/_nas_components/_distance_nas/_actual_penalty/__init__.py
vcs/_metrics/_nas/_nas_components/_distance_nas/_actual_penalty/_actual_penalty.py
vcs/_metrics/_nas/_nas_components/_distance_nas/_max_penalty/__init__.py
vcs/_metrics/_nas/_nas_components/_distance_nas/_max_penalty/_max_penalty.py
vcs/_metrics/_nas/_nas_components/_line_nas/__init__.py
vcs/_metrics/_nas/_nas_components/_line_nas/_line_nas.py
vcs/_metrics/_nas/_nas_components/_line_nas/_actual_line_length/__init__.py
vcs/_metrics/_nas/_nas_components/_line_nas/_actual_line_length/_actual_line_length.py
vcs/_metrics/_nas/_nas_components/_line_nas/_ideal_line_band/__init__.py
vcs/_metrics/_nas/_nas_components/_line_nas/_ideal_line_band/_ideal_line_band.py
vcs/_metrics/_nas/_nas_components/_regularize_nas/__init__.py
vcs/_metrics/_nas/_nas_components/_regularize_nas/_regularize_nas.py
vcs/_metrics/_vcs/__init__.py
vcs/_metrics/_vcs/_vcs.py
vcs/_segmenting/__init__.py
vcs/_segmenting/_segmenting.py
vcs/_utils/__init__.py
vcs/_utils/_utils.py
vcs/_visualize_vcs/__init__.py
vcs/_visualize_vcs/_best_match/__init__.py
vcs/_visualize_vcs/_best_match/visualizer.py
vcs/_visualize_vcs/_best_match/_utils/__init__.py
vcs/_visualize_vcs/_best_match/_utils/figure_generators.py
vcs/_visualize_vcs/_best_match/_utils/precision_details.py
vcs/_visualize_vcs/_best_match/_utils/recall_details.py
vcs/_visualize_vcs/_best_match/_utils/summary_table.py
video_comprehension_score-1.0.0.dist-info/licenses/LICENSE
video_comprehension_score-1.0.0.dist-info/METADATA
video_comprehension_score-1.0.0.dist-info/WHEEL
video_comprehension_score-1.0.0.dist-info/top_level.txt
video_comprehension_score-1.0.0.dist-info/RECORD
