Metadata-Version: 2.4
Name: video-comprehension-score
Version: 1.0.0
Summary: Video Comprehension Score (VCS) - A comprehensive metric for evaluating narrative similarity between reference and generated text
Author-email: Harsh Dubey <had7143@gmail.com>
Maintainer-email: Chulwoo Pack <chulwoo.pack@sdstate.edu>
License: MIT
Project-URL: Homepage, https://github.com/Multimodal-Intelligence-Lab/Video-Comprehension-Score
Project-URL: Documentation, https://multimodal-intelligence-lab.github.io/Video-Comprehension-Score/
Project-URL: Repository, https://github.com/Multimodal-Intelligence-Lab/Video-Comprehension-Score.git
Project-URL: Bug Tracker, https://github.com/Multimodal-Intelligence-Lab/Video-Comprehension-Score/issues
Project-URL: Changelog, https://github.com/Multimodal-Intelligence-Lab/Video-Comprehension-Score/blob/main/CHANGELOG.md
Keywords: text-similarity,narrative-analysis,nlp,video-comprehension,text-evaluation,semantic-similarity,alignment-metrics
Classifier: Development Status :: 5 - Production/Stable
Classifier: Intended Audience :: Developers
Classifier: Intended Audience :: Science/Research
Classifier: Operating System :: OS Independent
Classifier: Programming Language :: Python :: 3
Classifier: Programming Language :: Python :: 3.8
Classifier: Programming Language :: Python :: 3.9
Classifier: Programming Language :: Python :: 3.10
Classifier: Programming Language :: Python :: 3.11
Classifier: Programming Language :: Python :: 3.12
Classifier: Topic :: Scientific/Engineering :: Artificial Intelligence
Classifier: Topic :: Text Processing :: Linguistic
Classifier: Topic :: Software Development :: Libraries :: Python Modules
Requires-Python: >=3.8
License-File: LICENSE
Requires-Dist: numpy>=1.20.0
Requires-Dist: matplotlib>=3.5.0
Requires-Dist: seaborn>=0.11.0
Provides-Extra: dev
Requires-Dist: black>=21.0; extra == "dev"
Requires-Dist: isort>=5.0; extra == "dev"
Requires-Dist: flake8>=3.8; extra == "dev"
Requires-Dist: mypy>=0.910; extra == "dev"
Requires-Dist: pre-commit>=2.0; extra == "dev"
Provides-Extra: docs
Requires-Dist: sphinx>=4.0; extra == "docs"
Requires-Dist: sphinx-rtd-theme>=1.0; extra == "docs"
Requires-Dist: myst-parser>=0.15; extra == "docs"
Provides-Extra: all
Requires-Dist: video-comprehension-score[dev,docs]; extra == "all"
Dynamic: license-file
